example/__init__.py
example/gkn_bolts_survey.py
gkn_bolts_survey/__init__.py
gkn_bolts_survey/gkn_bolts_survey.py
gkn_bolts_survey/tests/__init__.py
gkn_bolts_survey/tests/test.py
gkn_bolts_survey/tests/test_AtlasCopco.xls
gkn_bolts_survey/tests/test_Excel.xlsx
gkn_bolts_survey-1.0.8.dist-info/LICENSE
gkn_bolts_survey-1.0.8.dist-info/METADATA
gkn_bolts_survey-1.0.8.dist-info/WHEEL
gkn_bolts_survey-1.0.8.dist-info/top_level.txt
gkn_bolts_survey-1.0.8.dist-info/RECORD
