Metadata-Version: 2.1
Name: gkn-bolts-survey
Version: 1.0.8
Summary: Print graphs out of tightening measures
Home-page: https://github.com/pypa/sampleproject
Author: Giuseppe Olivato
Author-email: giuseppe.olivato@gknautomotive.com
License: UNKNOWN
Platform: UNKNOWN
Classifier: Programming Language :: Python :: 3
Classifier: License :: OSI Approved :: MIT License
Classifier: Operating System :: OS Independent
Requires-Python: >=3.6
